alika/__init__.py
alika/app_functionality.py
alika/auth_service.py
alika/user_service.py
alika/api/api_responses.py
alika/api/api_service.py
Alika-0.0.1.dist-info/METADATA
Alika-0.0.1.dist-info/WHEEL
Alika-0.0.1.dist-info/top_level.txt
Alika-0.0.1.dist-info/RECORD
