Metadata-Version: 2.1
Name: Alika
Version: 0.0.1
Summary: Algida ile kazan unofficial api
Author: WarF0rPeace
Keywords: python,unofficial api
Classifier: Programming Language :: Python :: 3
Requires-Dist: requests
